[

    {
        "nombre": "Camiseta",
          "fecha_inicial" :"2022-02-20",
          "fecha_final" :"2023-02-20",
          "descripcion_producto": "camiseta Fnatic 2023",
          "cantidad": 20,
          "existencia": 20,
          "valor_normal": 254.9,
          "valor_con_descuento": 200,
          "condicion": "Nuevo",
          "imagen": "https://d3ugyf2ht6aenh.cloudfront.net/stores/001/440/198/products/fnatic-2023-frente1-27c900231f143b92b316747583425994-640-0.webp",
          "id_categoria_producto": 1,
          "id_comercio": 1
      },
      {
        "nombre": "Pantalon Rip Stop Negro - Hombre y Mujer",
        "fecha_inicial" :"2022-02-20",
        "fecha_final" :"2023-02-20",
        "descripcion_producto": "6 bolsillos: 2 a la altura de la cintura, 2 en la parte trasera y 2 bolsillos fuelle en los costados (tipo cargo), Entrepiernas y rodillas reforzadas ",
        "cantidad": 21,
        "existencia": 21,
        "valor_normal": 289.9,
        "valor_con_descuento": 210,
        "condicion": "Nuevo",
        "imagen": "https://alcatraz.com.ar/wp-content/uploads/2018/05/Pantalon-Ripstop-negro-frente-sin-cinto.jpg",
        "id_categoria_producto": 1,
        "id_comercio": 1
      },
      {
        "nombre": "microondas",
        "fecha_inicial" :"2022-02-20",
        "fecha_final" :"2023-02-20",
        "descripcion_producto": "Horno microondas",
        "cantidad": 12,
        "existencia": 12,
        "valor_normal": 399.9,
        "valor_con_descuento": 320,
        "condicion": "Reacondicionado",
        "imagen": "https://bgh.com.ar/wp-content/uploads/2020/08/Trifuncion-1280x720-1.png",
        "id_categoria_producto": 2,
        "id_comercio": 1


      },
      {
        "nombre": "Heladera",
        "fecha_inicial" :"2022-02-20",
        "fecha_final" :"2023-02-20",
        "descripcion_producto": "No Frost Electrolux DFN3000P Plata 265lts",
        "cantidad": 14,
        "existencia": 14,
        "valor_normal": 454.9,
        "valor_con_descuento": 400,
        "condicion": "Nuevo",
        "imagen": "https://electroluxar.vtexassets.com/arquivos/ids/159945/heladera-no-frost-electrolux-dfn3000p-plata-265lts-_Detalhe1.png?v=637541009901930000",
        "id_categoria_producto": 2,
        "id_comercio": 1
      },
      {
        "nombre": "mouse Fnatic",
        "fecha_inicial" :"2022-02-20",
        "fecha_final" :"2023-02-20",
        "descripcion_producto": "Fnatic Gear Bolt Wireless Gaming Mouse",
        "cantidad": 23,
        "existencia": 23,
        "valor_normal": 89.9,
        "valor_con_descuento": 200,
        "condicion": "Nuevo",
        "imagen": "https://us.maxgaming.com/bilder/artiklar/zoom/20946_1.jpg?m=1644594243",
        "id_categoria_producto": 3,
        "id_comercio": 1
      },
      {
        "nombre": "Teclado Fnatic",
        "fecha_inicial" :"2022-02-20",
        "fecha_final" :"2023-02-20",
        "descripcion_producto": "Ministreak Speed | Negro Led",
        "cantidad": 13,
        "existencia": 13,
        "valor_normal": 120.9,
        "valor_con_descuento": 200,
        "condicion": "Nuevo",
        "imagen": "https://http2.mlstatic.com/D_NQ_NP_774250-MLA46836566216_072021-O.webp",
        "id_categoria_producto": 3,
        "id_comercio": 1
      }, {
        "nombre": "rubor en crema",
        "fecha_inicial" :"2022-02-20",
        "fecha_final" :"2023-02-20",
        "descripcion_producto": "Rare Beauty By Selena Gomez Soft Pinch Liquid Blush- Love",
        "cantidad": 43,
        "existencia": 43,
        "valor_normal": 254.9,
        "valor_con_descuento": 200,
        "condicion": "Nuevo",
        "imagen": "https://http2.mlstatic.com/D_NQ_NP_674321-MLA54837913239_042023-O.webp",
        "id_categoria_producto": 4,
        "id_comercio": 1
      },
      {
        "nombre": "MAC SATIN LIPSTICK",
        "fecha_inicial" :"2022-02-20",
        "fecha_final" :"2023-02-20",
        "descripcion_producto": "MAC Lipstick el producto icónico que hizo famoso a MAC. Esta fórmulacremosa ofrece una sensación suave y acolchonada, cobertura construiblede media a completa y un acabado satinado.",
        "cantidad": 43,
        "existencia": 43,
        "valor_normal": 220.9,
        "valor_con_descuento": 200,
        "condicion": "Nuevo",
        "imagen": "https://juleriaque.vtexassets.com/arquivos/ids/204147-800-auto?v=638085758380170000&width=800&height=auto&aspect=true",
        "id_categoria_producto": 4,
        "id_comercio": 1
      },
      {
        "nombre": "Pan Integral",
        "fecha_inicial" :"2022-02-20",
        "fecha_final" :"2023-02-20",
        "descripcion_producto": "Pan Integral Bimbo 400 Gr.",
        "cantidad": 12,
        "existencia": 12,
        "valor_normal": 5.9,
        "valor_con_descuento": 3,
        "condicion": "Nuevo",
        "imagen": "https://supercristian.com.ar/wp-content/uploads/2020/08/84194-1.jpg",
        "id_categoria_producto": 5,
        "id_comercio": 1

      },
      {
        "nombre": "Galletitas Pitusas",
        "fecha_inicial" :"2022-02-20",
        "fecha_final" :"2023-02-20",
        "descripcion_producto": "Chocolate Mini Galletas Dulces Rellenas.",
        "cantidad": 11,
        "existencia": 11,
        "valor_normal": 11.9,
        "valor_con_descuento": 7,
        "condicion": "Nuevo",
        "imagen": "https://http2.mlstatic.com/D_NQ_NP_608904-MLA51442741719_092022-O.webp",
        "id_categoria_producto": 5,
        "id_comercio": 1
      },
      {
        "nombre": "2 Dinosaurios Juguetes ",
        "fecha_inicial" :"2022-02-20",
        "fecha_final" :"2023-02-20",
        "descripcion_producto": "Con Detalles Muy Reales.",
        "cantidad": 12,
        "existencia": 12,
        "valor_normal": 254.9,
        "valor_con_descuento": 200,
        "condicion": "Reacondicionado",
        "imagen": "https://jugueteriascarrousel.com.ar/wp-content/uploads/2020/07/bjjMesa-de-trabajo-1-copia.jpg",
        "id_categoria_producto": 6,
        "id_comercio": 1

    },
    {
        "nombre": "pokebolas de juguete",
        "fecha_inicial" :"2022-02-20",
        "fecha_final" :"2023-02-20",
        "descripcion_producto": "Con pokemon dentro.",
        "cantidad": 12,
        "existencia": 12,
        "valor_normal": 254.9,
        "valor_con_descuento": 200,
        "condicion": "Nuevo",
        "imagen": "https://ae01.alicdn.com/kf/H2afd675ea01942dba6e53a2d105e5c67M/TOMY-Pokemon-Elf-bola-pokebola-de-Pikachu-bolsillo-variante-de-monstruo-de-juguete-MODELO-DE-figura.jpg_Q90.jpg_.webp",
        "id_categoria_producto": 6,
        "id_comercio": 1

    },
    {
        "nombre": "Aparador Mueble ",
        "fecha_inicial" :"2022-02-20",
        "fecha_final" :"2023-02-20",
        "descripcion_producto": "Vajillero de 180cm Con Cajon",
        "cantidad": 11,
        "existencia": 11,
        "valor_normal": 2540.9,
        "valor_con_descuento": 2000,
        "condicion": "Nuevo",
        "imagen": "https://ciudad-muebles.com.ar/wp-content/uploads/2020/03/Aparado-Vajillero-5.jpg",
        "id_categoria_producto": 7,
        "id_comercio": 1

    },
    {
        "nombre": "Sillón Sofá ",
        "fecha_inicial" :"2022-02-20",
        "fecha_final" :"2023-02-20",
        "descripcion_producto": "3 Cuerpos Nápoles Premium",
        "cantidad": 21,
        "existencia": 21,
        "valor_normal": 2000.9,
        "valor_con_descuento": 1600,
        "condicion": "Reacondicionado",
        "imagen": "https://cortineriaconfort.com/wp-content/uploads/2022/04/sillon-sofa-3-cuerpos-napoles-premium-83779.jpg",
        "id_categoria_producto": 7,
        "id_comercio": 1
    },
    {
        "nombre": "Pala Corazón",
        "fecha_inicial" :"2022-02-20",
        "fecha_final" :"2023-02-20",
        "descripcion_producto": "68cm Cabo Madera Mango Plástico Camping Jardín",
        "cantidad": 121,
        "existencia": 121,
        "valor_normal": 254.9,
        "valor_con_descuento": 200,
        "condicion": "Reacondicionado",
        "imagen": "https://http2.mlstatic.com/D_NQ_NP_964536-MLA46941972173_082021-O.webp",
        "id_categoria_producto": 8,
        "id_comercio": 1
    },
    {
        "nombre": "Motosierra ligera",
        "fecha_inicial" :"2022-02-20",
        "fecha_final" :"2023-02-20",
        "descripcion_producto": "MS 180 C-BE",
        "cantidad": 121,
        "existencia": 121,
        "valor_normal": 254.9,
        "valor_con_descuento": 200,
        "condicion": "Reacondicionado",
        "imagen": "https://static.stihl.com/upload/assetmanager/modell_imagefilename/scaled/websize/128f09124a6445ffbb73783aa779ada9.jpg",
        "id_categoria_producto": 8,
        "id_comercio": 1
    },
    {
        "nombre": "Pelota De Voley Mikasa",
        "fecha_inicial" :"2022-02-20",
        "fecha_final" :"2023-02-20",
        "descripcion_producto": "Modelo Mva390 Rota Deportes",
        "cantidad": 121,
        "existencia": 121,
        "valor_normal": 254.9,
        "valor_con_descuento": 200,
        "condicion": "Reacondicionado",
        "imagen": "https://http2.mlstatic.com/D_NQ_NP_706814-MLA31030391926_062019-O.webp",
        "id_categoria_producto": 9,
        "id_comercio": 1
    },
    {
        "nombre": "Pelota adidas Argentina ",
        "fecha_inicial" :"2022-02-20",
        "fecha_final" :"2023-02-20",
        "descripcion_producto": "Al Rihla Club N°5",
        "cantidad": 121,
        "existencia": 121,
        "valor_normal": 254.9,
        "valor_con_descuento": 200,
        "condicion": "Reacondicionado",
        "imagen": "https://sporting.vtexassets.com/arquivos/ids/557628/6HM8141-000-1.jpg?v=637928169669670000",
        "id_categoria_producto": 9,
        "id_comercio": 1
    },
    {
        "nombre": "Aros Argolla",
        "fecha_inicial" :"2022-02-20",
        "fecha_final" :"2023-02-20",
        "descripcion_producto": "Oro 18 Kt",
        "cantidad": 121,
        "existencia": 121,
        "valor_normal": 254.9,
        "valor_con_descuento": 200,
        "condicion": "Reacondicionado",
        "imagen": "https://d2r9epyceweg5n.cloudfront.net/stores/001/986/989/products/13401-38561ab2eab643949116541096317760-1024-1024.jpg",
        "id_categoria_producto": 10,
        "id_comercio": 1
    },
    {
        "nombre": "Collar de cadena",
        "fecha_inicial" :"2022-02-20",
        "fecha_final" :"2023-02-20",
        "descripcion_producto": "Oro 14K de ancla clásico",
        "cantidad": 121,
        "existencia": 121,
        "valor_normal": 254.9,
        "valor_con_descuento": 200,
        "condicion": "Reacondicionado",
        "imagen": "https://pandoraar.vtexassets.com/arquivos/ids/255774-800-auto?v=637649481052100000&width=800&height=auto&aspect=true",
        "id_categoria_producto": 10,
        "id_comercio": 1
    },
    {
        "nombre": "MARTILLO GALPONERO",
        "fecha_inicial" :"2022-02-20",
        "fecha_final" :"2023-02-20",
        "descripcion_producto": "568 GRS CABO MADERA STANLEY",
        "cantidad": 121,
        "existencia": 121,
        "valor_normal": 254.9,
        "valor_con_descuento": 200,
        "condicion": "Reacondicionado",
        "imagen": "https://indufer.com.ar/wp-content/uploads/2018/07/martillo-carpintero-stanley-51271-D_NQ_NP_607618-MLV26988783339_032018-F-1.jpg",
        "id_categoria_producto": 11,
        "id_comercio": 1
    },
    {
        "nombre": "Tornillos",
        "fecha_inicial" :"2022-02-20",
        "fecha_final" :"2023-02-20",
        "descripcion_producto": "T2 Punta Aguja Para Durlock ",
        "cantidad": 121,
        "existencia": 121,
        "valor_normal": 254.9,
        "valor_con_descuento": 200,
        "condicion": "Reacondicionado",
        "imagen": "https://bercovichsa.vteximg.com.br/arquivos/ids/162388-1000-1000/tornillos-t2-punta-aguja-durlock-100-unidades-principal.jpg?v=637994476694200000",
        "id_categoria_producto": 11,
        "id_comercio": 1
    }
   
    ]